{
  "time_local": "2025-09-19T12:06:22",
  "hostname": "3989b856e384",
  "platform": "Linux-5.15.167.4-microsoft-standard-WSL2-x86_64-with-glibc2.41",
  "mac_address": "32:4b:40:ab:95:6f",
  "cpu": 2.8,
  "ramTotal": 8212471808,
  "ramUsed": 1036259328,
  "diskTotal": 1081101176832,
  "diskUsed": 2803494912,
  "processes": [
    {
      "pid": 1,
      "name": "python"
    }
  ],
  "connections": [
    {
      "laddr": "127.0.0.11:39073",
      "raddr": null,
      "status": "LISTEN",
      "pid": null
    },
    {
      "laddr": "127.0.0.11:38403",
      "raddr": null,
      "status": "NONE",
      "pid": null
    }
  ]
}